concierge/__init__.py
concierge/cli/__init__.py
concierge/cli/app.py
concierge/cli/commands/__init__.py
concierge/cli/commands/prepare.py
concierge/cli/commands/restore.py
concierge/cli/commands/status.py
concierge/config/__init__.py
concierge/config/loader.py
concierge/config/models.py
concierge/config/presets.py
concierge/core/__init__.py
concierge/core/executable.py
concierge/core/logging.py
concierge/core/manager.py
concierge/core/plan.py
concierge/juju/__init__.py
concierge/juju/credentials.py
concierge/juju/handler.py
concierge/packages/__init__.py
concierge/packages/deb_handler.py
concierge/packages/snap_handler.py
concierge/providers/__init__.py
concierge/providers/base.py
concierge/providers/factory.py
concierge/providers/google.py
concierge/providers/k8s.py
concierge/providers/lxd.py
concierge/providers/microk8s.py
concierge/system/__init__.py
concierge/system/command.py
concierge/system/models.py
concierge/system/runner.py
concierge/system/snap.py
concierge/system/worker.py
charm_concierge-0.1.0.dist-info/METADATA
charm_concierge-0.1.0.dist-info/WHEEL
charm_concierge-0.1.0.dist-info/entry_points.txt
charm_concierge-0.1.0.dist-info/RECORD
