Metadata-Version: 2.4
Name: charm-concierge
Version: 0.1.0
Summary: A tool to provision and manage charm development environments
Author-email: Tony Meyer <tony@aotearoa.dev>
License: Apache-2.0
Requires-Python: >=3.14
Requires-Dist: aiohttp>=3.9.0
Requires-Dist: pydantic>=2.6.0
Requires-Dist: pyyaml>=6.0
Requires-Dist: rich>=13.7.0
Requires-Dist: tenacity>=8.2.0
Requires-Dist: typer>=0.12.0
Provides-Extra: dev
Requires-Dist: pytest-asyncio>=0.23.0; extra == 'dev'
Requires-Dist: pytest-cov>=4.1.0; extra == 'dev'
Requires-Dist: pytest>=8.0.0; extra == 'dev'
Requires-Dist: ruff>=0.2.0; extra == 'dev'
Requires-Dist: ty>=0.0.1a34; extra == 'dev'
